setup.cfg
setup.py
src/pyokit/__init__.py
src/pyokit.egg-info/PKG-INFO
src/pyokit.egg-info/SOURCES.txt
src/pyokit.egg-info/dependency_links.txt
src/pyokit.egg-info/top_level.txt
src/pyokit/datastruct/__init__.py
src/pyokit/datastruct/genomicInterval.py
src/pyokit/datastruct/intervalTree.py
src/pyokit/datastruct/maf.py
src/pyokit/datastruct/sequence.py
src/pyokit/interface/__init__.py
src/pyokit/interface/cli.py
src/pyokit/io/__init__.py
src/pyokit/io/bedIterators.py
src/pyokit/io/bufferedWig.py
src/pyokit/io/fastaIterators.py
src/pyokit/io/fastqIterators.py
src/pyokit/io/indexedWig.py
src/pyokit/io/reference.py
src/pyokit/io/wigDir.py
src/pyokit/io/wigFile.py
src/pyokit/io/wigIterators.py
src/pyokit/statistics/__init__.py
src/pyokit/statistics/fisher.py
src/pyokit/statistics/probability.py
src/pyokit/testing/__init__.py
src/pyokit/testing/dummyfiles.py
src/pyokit/util/__init__.py
src/pyokit/util/fileUtils.py
src/pyokit/util/progressIndicator.py