Metadata-Version: 1.1
Name: pyokit
Version: 0.2.0
Summary: A library of python functions and classes to assist in processing high-throughput biological data
Home-page: https://github.com/pjuren/pyokit
Author: Philip J. Uren
Author-email: philip.uren@gmail.com
License: LGPL2
Download-URL: https://github.com/pjuren/pyokit/tarball/pyokit_0.2.0
Platform: UNKNOWN
